jupysql_plugin/__init__.py
jupysql_plugin/_version.py
jupysql_plugin/_widgets.py
jupysql_plugin/exceptions.py
jupysql_plugin/widgets/__init__.py
jupysql_plugin/widgets/connections.py
jupysql_plugin/widgets/connector_widget.py
jupysql_plugin/widgets/db_templates.py
jupysql_plugin-0.4.4.data/data/etc/jupyter/jupyter_server_config.d/jupysql_plugin.json
jupysql_plugin-0.4.4.data/data/share/jupyter/labextensions/jupysql-plugin/package.json
jupysql_plugin-0.4.4.data/data/share/jupyter/labextensions/jupysql-plugin/schemas/jupysql-plugin/package.json.orig
jupysql_plugin-0.4.4.data/data/share/jupyter/labextensions/jupysql-plugin/schemas/jupysql-plugin/settings.json
jupysql_plugin-0.4.4.data/data/share/jupyter/labextensions/jupysql-plugin/static/575.b9f8bfcbf03fcbba4eb0.js
jupysql_plugin-0.4.4.data/data/share/jupyter/labextensions/jupysql-plugin/static/592.050f1e29ce0751703fa6.js
jupysql_plugin-0.4.4.data/data/share/jupyter/labextensions/jupysql-plugin/static/7.a439e3f7d0c5ffc251e1.js
jupysql_plugin-0.4.4.data/data/share/jupyter/labextensions/jupysql-plugin/static/7.a439e3f7d0c5ffc251e1.js.LICENSE.txt
jupysql_plugin-0.4.4.data/data/share/jupyter/labextensions/jupysql-plugin/static/728.e3e5950acef93ec4338a.js
jupysql_plugin-0.4.4.data/data/share/jupyter/labextensions/jupysql-plugin/static/761.1f7307cb5f03d89ed782.js
jupysql_plugin-0.4.4.data/data/share/jupyter/labextensions/jupysql-plugin/static/761.1f7307cb5f03d89ed782.js.LICENSE.txt
jupysql_plugin-0.4.4.data/data/share/jupyter/labextensions/jupysql-plugin/static/884.22a788b22248cc4e32bd.js
jupysql_plugin-0.4.4.data/data/share/jupyter/labextensions/jupysql-plugin/static/90.1d56a674cfe73cb1faa4.js
jupysql_plugin-0.4.4.data/data/share/jupyter/labextensions/jupysql-plugin/static/remoteEntry.2eea65e287ef84987312.js
jupysql_plugin-0.4.4.data/data/share/jupyter/labextensions/jupysql-plugin/static/style.js
jupysql_plugin-0.4.4.data/data/share/jupyter/labextensions/jupysql-plugin/static/third-party-licenses.json
jupysql_plugin-0.4.4.dist-info/METADATA
jupysql_plugin-0.4.4.dist-info/WHEEL
jupysql_plugin-0.4.4.dist-info/licenses/LICENSE
jupysql_plugin-0.4.4.dist-info/RECORD
