Metadata-Version: 2.3
Name: jupysql-plugin
Version: 0.4.4
Dynamic: Keywords
Summary: Jupyterlab extension for JupySQL
Project-URL: Homepage, https://github.com/ploomber/jupysql-plugin.git
Project-URL: Bug Tracker, https://github.com/ploomber/jupysql-plugin.git/issues
Project-URL: Repository, https://github.com/ploomber/jupysql-plugin.git.git
Author-email: Ploomber <contact@ploomber.io>
License: BSD 3-Clause License
License-File: LICENSE
Classifier: Framework :: Jupyter
Classifier: Framework :: Jupyter :: JupyterLab
Classifier: Framework :: Jupyter :: JupyterLab :: 4
Classifier: Framework :: Jupyter :: JupyterLab :: Extensions
Classifier: Framework :: Jupyter :: JupyterLab :: Extensions :: Prebuilt
Classifier: License :: OSI Approved :: BSD License
Classifier: Programming Language :: Python
Classifier: Programming Language :: Python :: 3
Classifier: Programming Language :: Python :: 3.7
Classifier: Programming Language :: Python :: 3.8
Classifier: Programming Language :: Python :: 3.9
Classifier: Programming Language :: Python :: 3.10
Classifier: Programming Language :: Python :: 3.11
Requires-Python: >=3.7
Requires-Dist: ploomber-core
